{
  "!type": "GridRow_bs4", 
  "alignContent": "", 
  "alignItems": "", 
  "backgroundColor": "", 
  "borderColor": "#E0E0E0", 
  "borderStyle": "", 
  "borderWidth": "1", 
  "bottom": "auto", 
  "cached_js": "", 
  "cached_js_script_hash": "d41d8cd98f00b204e9800998ecf8427e", 
  "children": [
    {
      "!type": "External", 
      "file": [
        "forms", 
        "StockScreen", 
        "Elements", 
        "crdMarketCap.json"
      ]
    }, 
    {
      "!type": "External", 
      "file": [
        "forms", 
        "StockScreen", 
        "Elements", 
        "crdPe.json"
      ]
    }, 
    {
      "!type": "External", 
      "file": [
        "forms", 
        "StockScreen", 
        "Elements", 
        "crdEPS.json"
      ]
    }
  ], 
  "class": "", 
  "color": "", 
  "display": "flex", 
  "expanded_pmp": null, 
  "flexDirection": "", 
  "flexWrap": "wrap", 
  "fontFamily": "", 
  "fontSize": "", 
  "fontStyle": "", 
  "fontWeight": "", 
  "gutters": " no-gutters", 
  "height": "100", 
  "hidden": "display:none; ", 
  "id": "GridRow3", 
  "justifyContent": "", 
  "left": 0, 
  "mAll": "", 
  "mBottom": "", 
  "mLeft": "", 
  "mRight": "", 
  "mTop": "", 
  "onclick": "", 
  "onmousedown": "", 
  "onmousemove": "", 
  "onmouseout": "", 
  "onmouseup": "", 
  "onresize": "", 
  "ontouchend": "", 
  "ontouchmove": "", 
  "ontouchstart": "", 
  "pAll": "", 
  "pBottom": "", 
  "pLeft": "", 
  "pRight": "", 
  "pTop": "", 
  "position": "relative", 
  "right": "auto", 
  "rowClass": "", 
  "script": "", 
  "style": "", 
  "top": 240, 
  "verticalAlign": "", 
  "width": "100%"
}